composer_kit_mcp/__init__.py
composer_kit_mcp/server.py
composer_kit_mcp/components/__init__.py
composer_kit_mcp/components/data.py
composer_kit_mcp/components/models.py
composer_kit_mcp-0.7.2.dist-info/METADATA
composer_kit_mcp-0.7.2.dist-info/WHEEL
composer_kit_mcp-0.7.2.dist-info/entry_points.txt
composer_kit_mcp-0.7.2.dist-info/licenses/LICENSE
composer_kit_mcp-0.7.2.dist-info/RECORD
