Metadata-Version: 2.4
Name: composer_kit_mcp
Version: 0.7.2
Summary: A Model Context Protocol (MCP) server for Composer Kit UI components and Celo Composer project creation
Project-URL: Homepage, https://github.com/viral-sangani/composer-kit-mcp
Project-URL: Repository, https://github.com/viral-sangani/composer-kit-mcp
Project-URL: Documentation, https://github.com/viral-sangani/composer-kit-mcp#readme
Project-URL: Issues, https://github.com/viral-sangani/composer-kit-mcp/issues
Author-email: viral-sangani <viral.sangani2011@gmail.com>
License-File: LICENSE
Keywords: celo,celo-composer,components,composer-kit,dapp,mcp,react,ui,web3
Classifier: Development Status :: 3 - Alpha
Classifier: Intended Audience :: Developers
Classifier: License :: OSI Approved :: MIT License
Classifier: Programming Language :: Python :: 3
Requires-Python: >=3.11
Requires-Dist: mcp>=1.2.0
Requires-Dist: pydantic>=2.0.0
Provides-Extra: dev
Requires-Dist: black>=24.0.0; extra == 'dev'
Requires-Dist: mypy>=1.8.0; extra == 'dev'
Requires-Dist: pre-commit>=3.6.0; extra == 'dev'
Requires-Dist: pytest-asyncio>=0.23.0; extra == 'dev'
Requires-Dist: pytest>=8.0.0; extra == 'dev'
Requires-Dist: ruff>=0.1.0; extra == 'dev'
